README.rst
setup.py
cobrababel/__init__.py
cobrababel/bigg.py
cobrababel/compare.py
cobrababel/metanetx.py
cobrababel/source.py
cobrababel/translate.py
cobrababel/util.py
cobrababel/visual.py
cobrababel/vmh.py
cobrababel.egg-info/PKG-INFO
cobrababel.egg-info/SOURCES.txt
cobrababel.egg-info/dependency_links.txt
cobrababel.egg-info/requires.txt
cobrababel.egg-info/top_level.txt
cobrababel/kegg/KeggDatabase.py
cobrababel/kegg/KeggEnzyme.py
cobrababel/kegg/KeggEnzymeDatabase.py
cobrababel/kegg/KeggOrganism.py
cobrababel/kegg/KeggOrganismDatabase.py
cobrababel/kegg/KeggReaction.py
cobrababel/kegg/KeggReactionDatabase.py
cobrababel/kegg/__init__.py
cobrababel/kegg/kegg.py
cobrababel/test/__init__.py
cobrababel/test/conftest.py
cobrababel/test/test_bigg.py
cobrababel/test/test_kegg.py
cobrababel/test/test_metanetx.py
cobrababel/test/test_vmh.py