Metadata-Version: 1.1
Name: cobrababel
Version: 0.1.3
Summary: CobraBabel: COBRA Model Translator
Home-page: https://github.com/mmundy42/cobrababel
Author: Michael Mundy, Helena Mendes-Soares, Nicholas Chia
Author-email: mundy.michael@mayo.edu
License: BSD
Download-URL: https://pypi.python.org/pypi/cobrababel
Keywords: metabolism biology optimization flux balance analysis fba
Platform: GNU/Linux
Platform: Mac OS X >= 10.7
Platform: Microsoft Windows >= 7
Classifier: Development Status :: 3 - Alpha
Classifier: Environment :: Console
Classifier: Intended Audience :: Science/Research
Classifier: License :: OSI Approved :: BSD License
Classifier: Operating System :: OS Independent
Classifier: Programming Language :: Python :: 2.7
Classifier: Programming Language :: Python :: 3.4
Classifier: Programming Language :: Python :: 3.5
Classifier: Topic :: Scientific/Engineering
Classifier: Topic :: Scientific/Engineering :: Bio-Informatics
